lsattrdict/__init__.py
lsattrdict/default.py
lsattrdict/dictionary.py
lsattrdict/mapping.py
lsattrdict/merge.py
lsattrdict/mixins.py
lsattrdict-3.0.0.dist-info/entry_points.txt
lsattrdict-3.0.0.dist-info/LICENSE.txt
lsattrdict-3.0.0.dist-info/WHEEL
lsattrdict-3.0.0.dist-info/METADATA
lsattrdict-3.0.0.dist-info/RECORD
