Metadata-Version: 2.1
Name: lsattrdict
Version: 3.0.0
Summary: fork of dead AttrDict project
Author: Marco Bartel
Author-email: bsimpson888@gmail.com
Requires-Python: >=3.8.3,<4.0.0
Classifier: Programming Language :: Python :: 3
Classifier: Programming Language :: Python :: 3.9
